dezanza/__init__.py
dezanza/__main__.py
dezanza/tests/__init__.py
dezanza/tests/tests_dezanza.py
zanza/__init__.py
zanza/__main__.py
zanza/tests/__init__.py
zanza/tests/tests_zanza.py
zanza-0.1.0.dist-info/LICENSE
zanza-0.1.0.dist-info/METADATA
zanza-0.1.0.dist-info/WHEEL
zanza-0.1.0.dist-info/entry_points.txt
zanza-0.1.0.dist-info/top_level.txt
zanza-0.1.0.dist-info/RECORD
