Metadata-Version: 2.1
Name: zanza
Version: 0.1.0
Summary: Dead-simple string obfuscation library
Home-page: UNKNOWN
Author: fogasl
License: BSD-3-Clause
Keywords: simple string obfuscation
Platform: UNKNOWN
Requires-Python: >3
